Metadata-Version: 1.2
Name: pyxelrest
Version: 0.69.0
Summary: Access REST APIs from Excel using User Defined Functions (UDF)
Home-page: http://guru.trading.gdfsuez.net/bitbucket/projects/GEMS/repos/pyxelrest
Author: Engie
Author-email: colin.bounouar@engie.com
Maintainer: Engie
Maintainer-email: colin.bounouar@engie.com
License: UNKNOWN
Download-URL: http://www.engie.com
Keywords: excel,openapi,swagger,rest,udf,service
Platform: Windows
Classifier: Development Status :: 5 - Production/Stable
Classifier: Intended Audience :: Developers
Classifier: License :: OSI Approved :: MIT License
Classifier: Natural Language :: English
Classifier: Programming Language :: Python
Classifier: Programming Language :: Python :: 2
Classifier: Programming Language :: Python :: 2.7
Classifier: Programming Language :: Python :: 3
Classifier: Programming Language :: Python :: 3.5
Classifier: Programming Language :: Python :: 3.6
Classifier: Programming Language :: Python :: 3.7
Classifier: Operating System :: Microsoft :: Windows :: Windows 7
Requires-Python: >=2.7
